sensor_routing/__init__.py
sensor_routing/benefit_calculation.py
sensor_routing/econ_benefit.py
sensor_routing/econ_mapping.py
sensor_routing/econ_paths.py
sensor_routing/econ_route.py
sensor_routing/full_pipeline_cli.py
sensor_routing/hull_points_extraction.py
sensor_routing/path_finding.py
sensor_routing/point_mapping.py
sensor_routing/route_finding.py
sensor_routing-0.2.0.dist-info/licenses/LICENSE
sensor_routing-0.2.0.dist-info/METADATA
sensor_routing-0.2.0.dist-info/WHEEL
sensor_routing-0.2.0.dist-info/entry_points.txt
sensor_routing-0.2.0.dist-info/top_level.txt
sensor_routing-0.2.0.dist-info/RECORD
