Metadata-Version: 2.4
Name: sensor-routing
Version: 0.2.0
Summary: Optimal routing for CRNS mobile sensor data collection
Home-page: https://codebase.helmholtz.cloud/ufz/tb5-smm/met/wg7/sensor-routing
Author: Can Topaclioglu
Author-email: Can Topaclioglu <can.topaclioglu@ufz.de>
Maintainer-email: Can Topaclioglu <can.topaclioglu@ufz.de>
License: EUPL-1.2
Project-URL: Homepage, https://codebase.helmholtz.cloud/ufz/tb5-smm/met/wg7/sensor-routing
Project-URL: Repository, https://codebase.helmholtz.cloud/ufz/tb5-smm/met/wg7/sensor-routing
Project-URL: Issues, https://codebase.helmholtz.cloud/ufz/tb5-smm/met/wg7/sensor-routing/-/issues
Keywords: sensor-routing,CRNS,cosmic-ray-neutron-sensing,geospatial,routing-optimization,network-analysis,path-finding
Classifier: Development Status :: 4 - Beta
Classifier: Intended Audience :: Science/Research
Classifier: License :: OSI Approved :: European Union Public Licence 1.2 (EUPL 1.2)
Classifier: Operating System :: OS Independent
Classifier: Programming Language :: Python :: 3
Classifier: Programming Language :: Python :: 3.12
Classifier: Programming Language :: Python :: 3.13
Classifier: Topic :: Scientific/Engineering
Classifier: Topic :: Scientific/Engineering :: GIS
Requires-Python: >=3.12
License-File: LICENSE
Requires-Dist: numpy>=2.2.0
Requires-Dist: pandas>=2.2.3
Requires-Dist: geopandas>=1.0.1
Requires-Dist: osmnx>=2.0.0
Requires-Dist: shapely>=2.0.6
Requires-Dist: pyproj>=3.7.0
Requires-Dist: pyogrio>=0.10.0
Requires-Dist: networkx>=3.4.2
Requires-Dist: scipy>=1.11.0
Requires-Dist: scikit-learn>=1.3.0
Requires-Dist: pydantic>=2.0.0
Requires-Dist: annotated-types>=0.6.0
Requires-Dist: tqdm>=4.66.0
Requires-Dist: requests>=2.32.3
Provides-Extra: dev
Requires-Dist: pytest>=7.4.0; extra == "dev"
Requires-Dist: pytest-cov>=4.1.0; extra == "dev"
Requires-Dist: black>=23.0.0; extra == "dev"
Requires-Dist: flake8>=6.0.0; extra == "dev"
Requires-Dist: mypy>=1.5.0; extra == "dev"
Dynamic: author
Dynamic: home-page
Dynamic: license-file
Dynamic: requires-python
